itkwasm_mesh_io_wasi/__init__.py
itkwasm_mesh_io_wasi/_version.py
itkwasm_mesh_io_wasi/byu_read_mesh.py
itkwasm_mesh_io_wasi/byu_write_mesh.py
itkwasm_mesh_io_wasi/extension_to_mesh_io.py
itkwasm_mesh_io_wasi/extension_to_point_set_io.py
itkwasm_mesh_io_wasi/free_surfer_ascii_read_mesh.py
itkwasm_mesh_io_wasi/free_surfer_ascii_write_mesh.py
itkwasm_mesh_io_wasi/free_surfer_binary_read_mesh.py
itkwasm_mesh_io_wasi/free_surfer_binary_write_mesh.py
itkwasm_mesh_io_wasi/mesh_io_index.py
itkwasm_mesh_io_wasi/mz3_read_mesh.py
itkwasm_mesh_io_wasi/mz3_read_point_set.py
itkwasm_mesh_io_wasi/mz3_write_mesh.py
itkwasm_mesh_io_wasi/mz3_write_point_set.py
itkwasm_mesh_io_wasi/obj_read_mesh.py
itkwasm_mesh_io_wasi/obj_read_point_set.py
itkwasm_mesh_io_wasi/obj_write_mesh.py
itkwasm_mesh_io_wasi/obj_write_point_set.py
itkwasm_mesh_io_wasi/off_read_mesh.py
itkwasm_mesh_io_wasi/off_read_point_set.py
itkwasm_mesh_io_wasi/off_write_mesh.py
itkwasm_mesh_io_wasi/off_write_point_set.py
itkwasm_mesh_io_wasi/point_set_io_index.py
itkwasm_mesh_io_wasi/read_mesh.py
itkwasm_mesh_io_wasi/read_point_set.py
itkwasm_mesh_io_wasi/stl_read_mesh.py
itkwasm_mesh_io_wasi/stl_write_mesh.py
itkwasm_mesh_io_wasi/swc_read_mesh.py
itkwasm_mesh_io_wasi/swc_write_mesh.py
itkwasm_mesh_io_wasi/vtk_poly_data_read_mesh.py
itkwasm_mesh_io_wasi/vtk_poly_data_read_point_set.py
itkwasm_mesh_io_wasi/vtk_poly_data_write_mesh.py
itkwasm_mesh_io_wasi/vtk_poly_data_write_point_set.py
itkwasm_mesh_io_wasi/wasm_read_mesh.py
itkwasm_mesh_io_wasi/wasm_read_point_set.py
itkwasm_mesh_io_wasi/wasm_write_mesh.py
itkwasm_mesh_io_wasi/wasm_write_point_set.py
itkwasm_mesh_io_wasi/wasm_zstd_read_mesh.py
itkwasm_mesh_io_wasi/wasm_zstd_read_point_set.py
itkwasm_mesh_io_wasi/wasm_zstd_write_mesh.py
itkwasm_mesh_io_wasi/wasm_zstd_write_point_set.py
itkwasm_mesh_io_wasi/write_mesh.py
itkwasm_mesh_io_wasi/write_point_set.py
itkwasm_mesh_io_wasi/wasm_modules/byu-read-mesh.wasi.wasm
itkwasm_mesh_io_wasi-1.7.1.dist-info/METADATA
itkwasm_mesh_io_wasi-1.7.1.dist-info/WHEEL
itkwasm_mesh_io_wasi-1.7.1.dist-info/RECORD
