Metadata-Version: 2.3
Name: itkwasm-mesh-io-wasi
Version: 1.7.1
Summary: Input and output for scientific and medical image file formats.
Project-URL: Home, https://github.com/InsightSoftwareConsortium/ITK-Wasm
Project-URL: Source, https://github.com/InsightSoftwareConsortium/ITK-Wasm
Keywords: itkwasm,wasi,webassembly
Classifier: Development Status :: 4 - Beta
Classifier: Environment :: WebAssembly
Classifier: Environment :: WebAssembly :: Emscripten
Classifier: Environment :: WebAssembly :: WASI
Classifier: Intended Audience :: Developers
Classifier: Intended Audience :: Science/Research
Classifier: License :: OSI Approved :: Apache Software License
Classifier: Programming Language :: C++
Classifier: Programming Language :: Python
Classifier: Programming Language :: Python :: 3
Classifier: Programming Language :: Python :: 3.9
Classifier: Programming Language :: Python :: 3.10
Classifier: Programming Language :: Python :: 3.11
Classifier: Programming Language :: Python :: 3.12
Classifier: Programming Language :: Python :: 3.13
Requires-Python: >=3.9
Requires-Dist: importlib-resources
Requires-Dist: itkwasm>=1.0.b145
